{"status":"succeeded","createdDateTime":"2026-06-21T12:48:01Z","lastUpdatedDateTime":"2026-06-21T12:48:02Z","analyzeResult":{"apiVersion":"2024-11-30","modelId":"prebuilt-read","stringIndexType":"textElements","content":"3\nBUDDA BAKER SAFETY . CARDINALS\nOPTIC 0 DONRUSS","pages":[{"pageNumber":1,"angle":0,"width":1700,"height":2248,"unit":"pixel","words":[{"content":"3","polygon":[754,807,938,809,938,1003,754,999],"confidence":0.393,"span":{"offset":0,"length":1}},{"content":"BUDDA","polygon":[252,1892,503,1892,503,1944,252,1944],"confidence":0.997,"span":{"offset":2,"length":5}},{"content":"BAKER","polygon":[526,1892,753,1891,753,1944,526,1944],"confidence":0.998,"span":{"offset":8,"length":5}},{"content":"SAFETY","polygon":[257,1950,428,1948,427,1983,257,1983],"confidence":0.992,"span":{"offset":14,"length":6}},{"content":".","polygon":[449,1948,466,1948,466,1983,448,1983],"confidence":0.267,"span":{"offset":21,"length":1}},{"content":"CARDINALS","polygon":[485,1948,757,1947,757,1983,484,1983],"confidence":0.989,"span":{"offset":23,"length":9}},{"content":"OPTIC","polygon":[1239,1761,1389,1763,1389,1794,1239,1796],"confidence":0.995,"span":{"offset":33,"length":5}},{"content":"0","polygon":[1254,1798,1383,1801,1383,1920,1254,1919],"confidence":0.594,"span":{"offset":39,"length":1}},{"content":"DONRUSS","polygon":[1247,1943,1387,1943,1387,1962,1246,1962],"confidence":0.97,"span":{"offset":41,"length":7}}],"lines":[{"content":"3","polygon":[754,807,937,809,937,1004,757,998],"spans":[{"offset":0,"length":1}]},{"content":"BUDDA BAKER","polygon":[251,1892,752,1891,752,1942,251,1943],"spans":[{"offset":2,"length":11}]},{"content":"SAFETY . CARDINALS","polygon":[257,1948,756,1947,756,1982,257,1983],"spans":[{"offset":14,"length":18}]},{"content":"OPTIC","polygon":[1239,1761,1388,1761,1388,1795,1239,1795],"spans":[{"offset":33,"length":5}]},{"content":"0","polygon":[1254,1798,1376,1804,1382,1919,1257,1919],"spans":[{"offset":39,"length":1}]},{"content":"DONRUSS","polygon":[1245,1942,1386,1942,1386,1962,1245,1962],"spans":[{"offset":41,"length":7}]}],"spans":[{"offset":0,"length":48}]}],"paragraphs":[{"spans":[{"offset":0,"length":1}],"boundingRegions":[{"pageNumber":1,"polygon":[754,807,937,807,937,1004,754,1004]}],"content":"3"},{"spans":[{"offset":2,"length":30}],"boundingRegions":[{"pageNumber":1,"polygon":[251,1892,756,1891,756,1982,251,1983]}],"content":"BUDDA BAKER SAFETY . CARDINALS"},{"spans":[{"offset":33,"length":15}],"boundingRegions":[{"pageNumber":1,"polygon":[1239,1761,1388,1761,1388,1962,1239,1962]}],"content":"OPTIC 0 DONRUSS"}],"styles":[],"contentFormat":"text"}}