{"status":"succeeded","createdDateTime":"2026-06-21T14:05:39Z","lastUpdatedDateTime":"2026-06-21T14:05:41Z","analyzeResult":{"apiVersion":"2024-11-30","modelId":"prebuilt-read","stringIndexType":"textElements","content":"No. 16\nNFL\nNFLPA\nDEION SANDERS · CB\nAtlanta sports revolved around Sanders in 1992. On the gridiron, the star cornerback earned an All-Pro nod after snagging three interceptions and leading the league in kick-return yards. On the diamond, he batted .304 and led his league with 14 triples despite playing just 97 of baseball's 162-game schedule.\n· \"PRIME TIME\" SCORED TOUCHDOWNS SIX DIFFERENT WAYS\n· EIGHT-TIME PRO BOWL SELECTION AND SIX-TIME ALL-PRO FIRST TEAM\n· ONLY MAN TO PLAY IN THE SUPER BOWL AND WORLD SERIES\nPANINI\n2025 PANINI - DONRUSS OPTIC FOOTBALL THIEFE @ 2025 Panini America, Inc.","pages":[{"pageNumber":1,"angle":-89.45089721679688,"width":1692,"height":2232,"unit":"pixel","words":[{"content":"No.","polygon":[255,1951,258,1895,293,1895,292,1952],"confidence":0.994,"span":{"offset":0,"length":3}},{"content":"16","polygon":[236,1879,231,1793,291,1793,296,1875],"confidence":0.992,"span":{"offset":4,"length":2}},{"content":"NFL","polygon":[665,1995,665,1911,720,1911,720,1995],"confidence":0.977,"span":{"offset":7,"length":3}},{"content":"NFLPA","polygon":[682,1860,683,1751,742,1751,741,1860],"confidence":0.977,"span":{"offset":11,"length":5}},{"content":"DEION","polygon":[217,1630,217,1390,288,1391,284,1631],"confidence":0.997,"span":{"offset":17,"length":5}},{"content":"SANDERS","polygon":[218,1329,222,938,292,938,289,1329],"confidence":0.995,"span":{"offset":23,"length":7}},{"content":"·","polygon":[222,899,223,865,292,865,292,899],"confidence":0.305,"span":{"offset":31,"length":1}},{"content":"CB","polygon":[223,831,225,714,292,714,292,830],"confidence":0.997,"span":{"offset":33,"length":2}},{"content":"Atlanta","polygon":[327,1651,327,1533,372,1534,371,1652],"confidence":0.994,"span":{"offset":36,"length":7}},{"content":"sports","polygon":[327,1523,327,1420,373,1422,372,1524],"confidence":0.992,"span":{"offset":44,"length":6}},{"content":"revolved","polygon":[327,1410,328,1263,374,1265,373,1412],"confidence":0.993,"span":{"offset":51,"length":8}},{"content":"around","polygon":[328,1252,329,1135,375,1137,374,1254],"confidence":0.992,"span":{"offset":60,"length":6}},{"content":"Sanders","polygon":[329,1124,330,991,376,994,375,1126],"confidence":0.995,"span":{"offset":67,"length":7}},{"content":"in","polygon":[330,982,331,947,377,949,377,984],"confidence":0.998,"span":{"offset":75,"length":2}},{"content":"1992.","polygon":[331,930,332,830,378,833,377,932],"confidence":0.992,"span":{"offset":78,"length":5}},{"content":"On","polygon":[332,820,332,779,379,782,379,823],"confidence":0.994,"span":{"offset":84,"length":2}},{"content":"the","polygon":[332,769,333,712,380,715,379,771],"confidence":0.999,"span":{"offset":87,"length":3}},{"content":"gridiron,","polygon":[333,702,335,563,382,565,380,704],"confidence":0.992,"span":{"offset":91,"length":9}},{"content":"the","polygon":[335,553,336,496,384,499,383,556],"confidence":0.995,"span":{"offset":101,"length":3}},{"content":"star","polygon":[336,486,337,414,385,417,384,489],"confidence":0.992,"span":{"offset":105,"length":4}},{"content":"cornerback","polygon":[384,1652,385,1461,430,1462,426,1653],"confidence":0.992,"span":{"offset":110,"length":10}},{"content":"earned","polygon":[385,1450,386,1333,432,1334,430,1451],"confidence":0.992,"span":{"offset":121,"length":6}},{"content":"an","polygon":[386,1322,386,1282,433,1283,432,1323],"confidence":0.996,"span":{"offset":128,"length":2}},{"content":"All-Pro","polygon":[386,1272,387,1157,435,1159,433,1273],"confidence":0.983,"span":{"offset":131,"length":7}},{"content":"nod","polygon":[387,1147,388,1080,436,1082,435,1148],"confidence":0.997,"span":{"offset":139,"length":3}},{"content":"after","polygon":[388,1069,389,989,438,990,436,1071],"confidence":0.993,"span":{"offset":143,"length":5}},{"content":"snagging","polygon":[389,979,390,830,440,832,438,980],"confidence":0.993,"span":{"offset":149,"length":8}},{"content":"three","polygon":[390,820,391,730,441,732,440,821],"confidence":0.995,"span":{"offset":158,"length":5}},{"content":"interceptions","polygon":[392,720,394,496,444,498,441,722],"confidence":0.992,"span":{"offset":164,"length":13}},{"content":"and","polygon":[394,486,395,424,445,427,444,488],"confidence":0.998,"span":{"offset":178,"length":3}},{"content":"leading","polygon":[395,414,397,283,446,283,445,416],"confidence":0.996,"span":{"offset":182,"length":7}},{"content":"the","polygon":[443,1652,443,1600,486,1601,486,1653],"confidence":0.998,"span":{"offset":190,"length":3}},{"content":"league","polygon":[443,1591,444,1475,487,1476,487,1592],"confidence":0.996,"span":{"offset":194,"length":6}},{"content":"in","polygon":[444,1466,445,1434,488,1435,487,1467],"confidence":0.998,"span":{"offset":201,"length":2}},{"content":"kick-return","polygon":[445,1422,447,1237,489,1237,488,1422],"confidence":0.992,"span":{"offset":204,"length":11}},{"content":"yards.","polygon":[447,1224,448,1119,490,1120,489,1225],"confidence":0.993,"span":{"offset":216,"length":6}},{"content":"On","polygon":[448,1110,448,1067,491,1068,490,1111],"confidence":0.998,"span":{"offset":223,"length":2}},{"content":"the","polygon":[448,1058,449,1001,491,1001,491,1058],"confidence":0.999,"span":{"offset":226,"length":3}},{"content":"diamond,","polygon":[449,991,451,836,493,836,491,991],"confidence":0.994,"span":{"offset":230,"length":8}},{"content":"he","polygon":[451,827,451,783,493,783,493,827],"confidence":0.992,"span":{"offset":239,"length":2}},{"content":"batted","polygon":[451,774,452,667,494,667,493,774],"confidence":0.995,"span":{"offset":242,"length":6}},{"content":".304","polygon":[452,657,453,578,495,578,494,657],"confidence":0.992,"span":{"offset":249,"length":4}},{"content":"and","polygon":[453,563,454,505,495,505,495,563],"confidence":0.997,"span":{"offset":254,"length":3}},{"content":"led","polygon":[454,496,454,439,496,439,496,496],"confidence":0.995,"span":{"offset":258,"length":3}},{"content":"his","polygon":[454,429,455,377,497,377,496,429],"confidence":0.996,"span":{"offset":262,"length":3}},{"content":"league","polygon":[503,1653,504,1539,546,1538,545,1653],"confidence":0.995,"span":{"offset":266,"length":6}},{"content":"with","polygon":[504,1529,504,1458,547,1458,546,1528],"confidence":0.992,"span":{"offset":273,"length":4}},{"content":"14","polygon":[504,1443,504,1403,547,1403,547,1443],"confidence":0.998,"span":{"offset":278,"length":2}},{"content":"triples","polygon":[505,1393,505,1282,548,1281,547,1393],"confidence":0.995,"span":{"offset":281,"length":7}},{"content":"despite","polygon":[505,1272,507,1149,550,1149,548,1272],"confidence":0.995,"span":{"offset":289,"length":7}},{"content":"playing","polygon":[507,1139,508,1016,551,1016,550,1139],"confidence":0.997,"span":{"offset":297,"length":7}},{"content":"just","polygon":[508,1007,509,938,552,938,551,1006],"confidence":0.992,"span":{"offset":305,"length":4}},{"content":"97","polygon":[509,929,509,884,552,883,552,929],"confidence":0.998,"span":{"offset":310,"length":2}},{"content":"of","polygon":[509,874,510,842,553,841,552,874],"confidence":0.998,"span":{"offset":313,"length":2}},{"content":"baseball's","polygon":[510,833,512,657,554,657,553,832],"confidence":0.993,"span":{"offset":316,"length":10}},{"content":"162-game","polygon":[512,645,515,478,556,477,554,645],"confidence":0.993,"span":{"offset":327,"length":8}},{"content":"schedule.","polygon":[515,465,517,297,557,297,556,465],"confidence":0.993,"span":{"offset":336,"length":9}},{"content":"·","polygon":[609,1643,609,1621,646,1620,645,1643],"confidence":0.129,"span":{"offset":346,"length":1}},{"content":"\"PRIME","polygon":[609,1612,610,1485,648,1485,646,1612],"confidence":0.992,"span":{"offset":348,"length":6}},{"content":"TIME\"","polygon":[610,1474,611,1377,650,1377,649,1473],"confidence":0.977,"span":{"offset":355,"length":5}},{"content":"SCORED","polygon":[611,1366,612,1238,652,1238,650,1365],"confidence":0.999,"span":{"offset":361,"length":6}},{"content":"TOUCHDOWNS","polygon":[612,1222,615,986,655,987,652,1222],"confidence":0.996,"span":{"offset":368,"length":10}},{"content":"SIX","polygon":[615,975,616,922,656,922,655,975],"confidence":0.998,"span":{"offset":379,"length":3}},{"content":"DIFFERENT","polygon":[616,911,618,732,657,732,656,911],"confidence":0.996,"span":{"offset":383,"length":9}},{"content":"WAYS","polygon":[618,723,619,627,658,627,657,723],"confidence":0.992,"span":{"offset":393,"length":4}},{"content":"·","polygon":[671,1639,671,1620,709,1621,709,1640],"confidence":0.711,"span":{"offset":398,"length":1}},{"content":"EIGHT-TIME","polygon":[671,1611,672,1420,711,1421,709,1612],"confidence":0.992,"span":{"offset":400,"length":10}},{"content":"PRO","polygon":[673,1411,673,1346,712,1347,711,1412],"confidence":0.996,"span":{"offset":411,"length":3}},{"content":"BOWL","polygon":[673,1335,674,1238,713,1239,712,1335],"confidence":0.992,"span":{"offset":415,"length":4}},{"content":"SELECTION","polygon":[674,1227,676,1054,715,1055,713,1228],"confidence":0.995,"span":{"offset":420,"length":9}},{"content":"AND","polygon":[676,1037,677,972,716,973,715,1038],"confidence":0.995,"span":{"offset":430,"length":3}},{"content":"SIX-TIME","polygon":[677,955,679,808,718,809,716,956],"confidence":0.992,"span":{"offset":434,"length":8}},{"content":"ALL-PRO","polygon":[679,799,680,662,720,663,718,800],"confidence":0.995,"span":{"offset":443,"length":7}},{"content":"FIRST","polygon":[681,650,682,552,722,553,720,652],"confidence":0.995,"span":{"offset":451,"length":5}},{"content":"TEAM","polygon":[682,543,684,451,723,451,722,544],"confidence":0.988,"span":{"offset":457,"length":4}},{"content":"·","polygon":[734,1640,734,1621,772,1621,772,1641],"confidence":0.362,"span":{"offset":462,"length":1}},{"content":"ONLY","polygon":[734,1612,734,1528,773,1528,772,1612],"confidence":0.989,"span":{"offset":464,"length":4}},{"content":"MAN","polygon":[734,1519,735,1445,774,1446,773,1519],"confidence":0.999,"span":{"offset":469,"length":3}},{"content":"TO","polygon":[735,1429,735,1391,775,1392,774,1429],"confidence":0.999,"span":{"offset":473,"length":2}},{"content":"PLAY","polygon":[735,1380,736,1293,776,1294,775,1380],"confidence":0.989,"span":{"offset":476,"length":4}},{"content":"IN","polygon":[736,1284,736,1255,776,1255,776,1285],"confidence":0.999,"span":{"offset":481,"length":2}},{"content":"THE","polygon":[736,1235,737,1175,777,1175,776,1236],"confidence":0.999,"span":{"offset":484,"length":3}},{"content":"SUPER","polygon":[737,1163,738,1056,778,1056,777,1164],"confidence":0.999,"span":{"offset":488,"length":5}},{"content":"BOWL","polygon":[738,1045,739,948,779,948,778,1045],"confidence":0.992,"span":{"offset":494,"length":4}},{"content":"AND","polygon":[739,936,740,871,780,871,779,937],"confidence":0.999,"span":{"offset":499,"length":3}},{"content":"WORLD","polygon":[740,859,742,742,781,742,780,859],"confidence":0.995,"span":{"offset":503,"length":5}},{"content":"SERIES","polygon":[742,728,743,613,782,613,781,728],"confidence":0.997,"span":{"offset":509,"length":6}},{"content":"PANINI","polygon":[1434,2068,1436,1872,1471,1873,1469,2069],"confidence":0.992,"span":{"offset":516,"length":6}},{"content":"2025","polygon":[1442,1843,1443,1769,1474,1769,1472,1843],"confidence":0.989,"span":{"offset":523,"length":4}},{"content":"PANINI","polygon":[1443,1758,1444,1656,1476,1656,1474,1758],"confidence":0.992,"span":{"offset":528,"length":6}},{"content":"-","polygon":[1444,1649,1444,1634,1476,1634,1476,1650],"confidence":0.988,"span":{"offset":535,"length":1}},{"content":"DONRUSS","polygon":[1444,1623,1446,1491,1478,1492,1476,1623],"confidence":0.995,"span":{"offset":537,"length":7}},{"content":"OPTIC","polygon":[1446,1480,1447,1401,1480,1402,1478,1480],"confidence":0.989,"span":{"offset":545,"length":5}},{"content":"FOOTBALL","polygon":[1447,1390,1449,1254,1482,1255,1480,1391],"confidence":0.988,"span":{"offset":551,"length":8}},{"content":"THIEFE","polygon":[1450,1233,1452,1150,1483,1151,1482,1234],"confidence":0.167,"span":{"offset":560,"length":6}},{"content":"@","polygon":[1452,1133,1452,1118,1484,1119,1484,1134],"confidence":0.157,"span":{"offset":567,"length":1}},{"content":"2025","polygon":[1453,1102,1454,1038,1485,1039,1484,1103],"confidence":0.989,"span":{"offset":569,"length":4}},{"content":"Panini","polygon":[1454,1031,1456,952,1486,953,1485,1032],"confidence":0.989,"span":{"offset":574,"length":6}},{"content":"America,","polygon":[1456,945,1459,835,1488,837,1486,946],"confidence":0.987,"span":{"offset":581,"length":8}},{"content":"Inc.","polygon":[1459,829,1461,775,1489,776,1488,830],"confidence":0.977,"span":{"offset":590,"length":4}}],"lines":[{"content":"No.","polygon":[255,1952,260,1895,292,1895,292,1952],"spans":[{"offset":0,"length":3}]},{"content":"16","polygon":[236,1879,230,1793,291,1793,295,1877],"spans":[{"offset":4,"length":2}]},{"content":"NFL","polygon":[665,1996,665,1912,719,1911,720,1997],"spans":[{"offset":7,"length":3}]},{"content":"NFLPA","polygon":[682,1859,683,1751,741,1752,741,1862],"spans":[{"offset":11,"length":5}]},{"content":"DEION SANDERS · CB","polygon":[217,1630,224,714,293,714,286,1631],"spans":[{"offset":17,"length":18}]},{"content":"Atlanta sports revolved around Sanders in 1992. On the gridiron, the star","polygon":[327,1652,336,414,384,414,373,1652],"spans":[{"offset":36,"length":73}]},{"content":"cornerback earned an All-Pro nod after snagging three interceptions and leading","polygon":[384,1653,397,283,446,284,429,1653],"spans":[{"offset":110,"length":79}]},{"content":"the league in kick-return yards. On the diamond, he batted .304 and led his","polygon":[443,1652,454,377,497,377,486,1653],"spans":[{"offset":190,"length":75}]},{"content":"league with 14 triples despite playing just 97 of baseball's 162-game schedule.","polygon":[503,1653,515,297,558,297,544,1654],"spans":[{"offset":266,"length":79}]},{"content":"· \"PRIME TIME\" SCORED TOUCHDOWNS SIX DIFFERENT WAYS","polygon":[609,1643,619,627,658,627,647,1644],"spans":[{"offset":346,"length":51}]},{"content":"· EIGHT-TIME PRO BOWL SELECTION AND SIX-TIME ALL-PRO FIRST TEAM","polygon":[671,1640,683,451,722,451,709,1640],"spans":[{"offset":398,"length":63}]},{"content":"· ONLY MAN TO PLAY IN THE SUPER BOWL AND WORLD SERIES","polygon":[734,1640,743,613,782,613,772,1640],"spans":[{"offset":462,"length":53}]},{"content":"PANINI","polygon":[1434,2068,1436,1872,1471,1872,1469,2069],"spans":[{"offset":516,"length":6}]},{"content":"2025 PANINI - DONRUSS OPTIC FOOTBALL THIEFE @ 2025 Panini America, Inc.","polygon":[1442,1843,1457,775,1489,776,1472,1844],"spans":[{"offset":523,"length":71}]}],"spans":[{"offset":0,"length":594}]}],"paragraphs":[{"spans":[{"offset":0,"length":6}],"boundingRegions":[{"pageNumber":1,"polygon":[238,1955,230,1793,291,1790,299,1952]}],"content":"No. 16"},{"spans":[{"offset":7,"length":3}],"boundingRegions":[{"pageNumber":1,"polygon":[665,1998,664,1912,719,1911,720,1997]}],"content":"NFL"},{"spans":[{"offset":11,"length":5}],"boundingRegions":[{"pageNumber":1,"polygon":[682,1861,683,1751,742,1752,741,1862]}],"content":"NFLPA"},{"spans":[{"offset":17,"length":18}],"boundingRegions":[{"pageNumber":1,"polygon":[217,1630,224,713,293,714,286,1631]}],"content":"DEION SANDERS · CB"},{"spans":[{"offset":36,"length":309}],"boundingRegions":[{"pageNumber":1,"polygon":[323,1652,337,282,558,285,544,1655]}],"content":"Atlanta sports revolved around Sanders in 1992. On the gridiron, the star cornerback earned an All-Pro nod after snagging three interceptions and leading the league in kick-return yards. On the diamond, he batted .304 and led his league with 14 triples despite playing just 97 of baseball's 162-game schedule."},{"spans":[{"offset":346,"length":51}],"boundingRegions":[{"pageNumber":1,"polygon":[608,1644,619,627,658,627,647,1644]}],"content":"· \"PRIME TIME\" SCORED TOUCHDOWNS SIX DIFFERENT WAYS"},{"spans":[{"offset":398,"length":63}],"boundingRegions":[{"pageNumber":1,"polygon":[671,1640,683,451,722,451,710,1640]}],"content":"· EIGHT-TIME PRO BOWL SELECTION AND SIX-TIME ALL-PRO FIRST TEAM"},{"spans":[{"offset":462,"length":53}],"boundingRegions":[{"pageNumber":1,"polygon":[734,1640,743,613,782,613,773,1640]}],"content":"· ONLY MAN TO PLAY IN THE SUPER BOWL AND WORLD SERIES"},{"spans":[{"offset":516,"length":6}],"boundingRegions":[{"pageNumber":1,"polygon":[1434,2069,1436,1872,1471,1872,1469,2069]}],"content":"PANINI"},{"spans":[{"offset":523,"length":71}],"boundingRegions":[{"pageNumber":1,"polygon":[1440,1843,1457,775,1489,776,1472,1844]}],"content":"2025 PANINI - DONRUSS OPTIC FOOTBALL THIEFE @ 2025 Panini America, Inc."}],"styles":[],"contentFormat":"text"}}